{
    "possibly_sensitive": false,
    "contributors": null,
    "in_reply_to_status_id": null,
    "filter_level": "low",
    "in_reply_to_user_id": null,
    "extended_entities": {
        "media": [
            {
                "expanded_url": "http://twitter.com/enthalpychange/status/630019514936078336/photo/1",
                "id_str": "630019497324220416",
                "url": "http://t.co/SKoF4W2If1",
                "display_url": "pic.twitter.com/SKoF4W2If1",
                "id": 630019497324220400,
                "media_url": "http://pbs.twimg.com/media/CL5HZROUkAAqPrR.jpg",
                "sizes": {
                    "small": {
                        "h": 452,
                        "resize": "fit",
                        "w": 340
                    },
                    "thumb": {
                        "h": 150,
                        "resize": "crop",
                        "w": 150
                    },
                    "large": {
                        "h": 852,
                        "resize": "fit",
                        "w": 640
                    },
                    "medium": {
                        "h": 798,
                        "resize": "fit",
                        "w": 600
                    }
                },
                "indices": [
                    19,
                    41
                ],
                "media_url_https": "https://pbs.twimg.com/media/CL5HZROUkAAqPrR.jpg",
                "type": "photo"
            }
        ]
    },
    "lang": "en",
    "coordinates": null,
    "source": "<a href=\"http://twitter.com/download/iphone\" rel=\"nofollow\">Twitter for iPhone</a>",
    "created_at": "Sat Aug 08 14:15:32 +0000 2015",
    "place": {
        "country_code": "KZ",
        "attributes": {},
        "full_name": "Kazakhstan",
        "url": "https://api.twitter.com/1.1/geo/id/6d73a696edc5306f.json",
        "bounding_box": {
            "coordinates": [
                [
                    [
                        46.4925433,
                        40.9363327
                    ],
                    [
                        46.4925433,
                        55.4425719
                    ],
                    [
                        87.3152134,
                        55.4425719
                    ],
                    [
                        87.3152134,
                        40.9363327
                    ]
                ]
            ],
            "type": "Polygon"
        },
        "id": "6d73a696edc5306f",
        "place_type": "country",
        "name": "Kazakhstan",
        "country": "Kazakhstan"
    },
    "timestamp_ms": "1439043332214",
    "text": "hooh starter pack: http://t.co/SKoF4W2If1",
    "geo": null,
    "user": {
        "profile_sidebar_border_color": "C0DEED",
        "screen_name": "enthalpychange",
        "lang": "en",
        "listed_count": 0,
        "profile_use_background_image": true,
        "profile_image_url_https": "https://pbs.twimg.com/profile_images/629703196944916480/BZQibLwS_normal.jpg",
        "contributors_enabled": false,
        "geo_enabled": true,
        "profile_background_tile": false,
        "id_str": "2330946779",
        "profile_sidebar_fill_color": "DDEEF6",
        "utc_offset": null,
        "following": null,
        "verified": false,
        "location": "uk",
        "favourites_count": 402,
        "description": "i kinda live in england ⚫️ put my life in the hands of a rock n roll band who threw it all away",
        "profile_text_color": "333333",
        "statuses_count": 2428,
        "default_profile": true,
        "notifications": null,
        "follow_request_sent": null,
        "friends_count": 73,
        "name": "kane you not plz ",
        "protected": false,
        "is_translator": false,
        "profile_banner_url": "https://pbs.twimg.com/profile_banners/2330946779/1435234767",
        "url": null,
        "profile_image_url": "http://pbs.twimg.com/profile_images/629703196944916480/BZQibLwS_normal.jpg",
        "time_zone": null,
        "profile_background_color": "C0DEED",
        "id": 2330946779,
        "created_at": "Fri Feb 07 22:35:14 +0000 2014",
        "profile_background_image_url_https": "https://abs.twimg.com/images/themes/theme1/bg.png",
        "followers_count": 35,
        "default_profile_image": false,
        "profile_link_color": "0084B4",
        "profile_background_image_url": "http://abs.twimg.com/images/themes/theme1/bg.png"
    },
    "favorite_count": 0,
    "in_reply_to_user_id_str": null,
    "truncated": false,
    "id_str": "630019514936078336",
    "in_reply_to_screen_name": null,
    "in_reply_to_status_id_str": null,
    "retweeted": false,
    "id": 630019514936078300,
    "retweet_count": 0,
    "favorited": false,
    "entities": {
        "hashtags": [],
        "trends": [],
        "user_mentions": [],
        "urls": [],
        "symbols": [],
        "media": [
            {
                "expanded_url": "http://twitter.com/enthalpychange/status/630019514936078336/photo/1",
                "id_str": "630019497324220416",
                "url": "http://t.co/SKoF4W2If1",
                "display_url": "pic.twitter.com/SKoF4W2If1",
                "id": 630019497324220400,
                "media_url": "http://pbs.twimg.com/media/CL5HZROUkAAqPrR.jpg",
                "sizes": {
                    "small": {
                        "h": 452,
                        "resize": "fit",
                        "w": 340
                    },
                    "thumb": {
                        "h": 150,
                        "resize": "crop",
                        "w": 150
                    },
                    "large": {
                        "h": 852,
                        "resize": "fit",
                        "w": 640
                    },
                    "medium": {
                        "h": 798,
                        "resize": "fit",
                        "w": 600
                    }
                },
                "indices": [
                    19,
                    41
                ],
                "media_url_https": "https://pbs.twimg.com/media/CL5HZROUkAAqPrR.jpg",
                "type": "photo"
            }
        ]
    }
}
